{
  "db_name": "PostgreSQL",
  "query": "SELECT id, name, refresh_token_hash, refresh_expires_at, last_seen,\n             status as \"status: WorkerStatus\", capabilities, created_at as \"created_at!: DateTime<Utc>\",\n             active_jobs, max_concurrent_jobs\n             FROM workers WHERE refresh_token_hash = $1",
  "describe": {
    "columns": [
      {
        "ordinal": 0,
        "name": "id",
        "type_info": "Uuid"
      },
      {
        "ordinal": 1,
        "name": "name",
        "type_info": "Text"
      },
      {
        "ordinal": 2,
        "name": "refresh_token_hash",
        "type_info": "Text"
      },
      {
        "ordinal": 3,
        "name": "refresh_expires_at",
        "type_info": "Timestamptz"
      },
      {
        "ordinal": 4,
        "name": "last_seen",
        "type_info": "Timestamptz"
      },
      {
        "ordinal": 5,
        "name": "status: WorkerStatus",
        "type_info": {
          "Custom": {
            "name": "worker_status",
            "kind": {
              "Enum": [
                "idle",
                "busy",
                "disconnected"
              ]
            }
          }
        }
      },
      {
        "ordinal": 6,
        "name": "capabilities",
        "type_info": "Jsonb"
      },
      {
        "ordinal": 7,
        "name": "created_at!: DateTime<Utc>",
        "type_info": "Timestamptz"
      },
      {
        "ordinal": 8,
        "name": "active_jobs",
        "type_info": "Int4"
      },
      {
        "ordinal": 9,
        "name": "max_concurrent_jobs",
        "type_info": "Int4"
      }
    ],
    "parameters": {
      "Left": [
        "Text"
      ]
    },
    "nullable": [
      false,
      false,
      false,
      false,
      true,
      false,
      true,
      true,
      false,
      false
    ]
  },
  "hash": "ada1fac325e7086f55a4425f320d6e870a08680759175e95105fbb451fce1c39"
}
